LICENSE
README.md
setup.py
anachronos/__init__.py
anachronos/configuration.py
anachronos/exceptions.py
anachronos/message.py
anachronos/setup.py
anachronos.egg-info/PKG-INFO
anachronos.egg-info/SOURCES.txt
anachronos.egg-info/dependency_links.txt
anachronos.egg-info/top_level.txt
anachronos/communication/__init__.py
anachronos/communication/anachronos_client.py
anachronos/communication/logging_interfaces.py
anachronos/communication/message_queue_consumer.py
anachronos/compat/__init__.py
anachronos/compat/jivago_streams.py
anachronos/test/__init__.py
anachronos/test/assertion.py
anachronos/test/assertion_fixture.py
anachronos/test/assertion_runner.py
anachronos/test/registering_assertion_fixture.py
anachronos/test/assertions/__init__.py
anachronos/test/assertions/order_comparison.py
anachronos/test/assertions/schedule.py
anachronos/test/assertions/unary.py
anachronos/test/assertions/uncaught_exception_assertion.py
anachronos/test/boot/__init__.py
anachronos/test/boot/application_runner.py
anachronos/test/boot/test.py
anachronos/test/boot/test_case.py
anachronos/test/boot/test_runner.py
anachronos/test/boot/test_suite.py
anachronos/test/formatting/__init__.py
anachronos/test/formatting/report_formatter.py
anachronos/test/formatting/stdout_report_formatter.py
anachronos/test/reporting/__init__.py
anachronos/test/reporting/test_report.py
anachronos/test/reporting/test_report_index.py
anachronos/test/reporting/test_result.py
anachronos/test/reporting/test_status.py
anachronos/util/__init__.py
anachronos/util/http_requester.py