Metadata-Version: 2.1
Name: anachronos
Version: 0.0.7
Summary: A testing framework for testing frameworks.
Home-page: https://github.com/keotl/anachronos
Author: Kento A. Lauzon
Author-email: kento.lauzon@ligature.ca
Classifier: Development Status :: 3 - Alpha
Classifier: Intended Audience :: Developers
Classifier: Topic :: Software Development :: Testing
Classifier: License :: OSI Approved :: GNU General Public License v3 (GPLv3)
Classifier: Programming Language :: Python :: 3.6
Classifier: Programming Language :: Python :: 3.7
License-File: LICENSE
